rpart/DecisionTree-trythis/DecisionTree.py
rpart/DecisionTree-trythis/Node.py
rpart/DecisionTree-trythis/RandomForestClassifier.py
rpart/DecisionTree-trythis/train.py
rpart/DecisionTree-trythis/utils.py
rpart/DecisionTree-trythis/visualize_tree.py
rpart/DecisionTreeClassifier.py
rpart/Node.py
rpart/RandomForestClassifier.py
rpart/__init__.py
rpart/dataset.py
rpart/entropy.py
rpart/utils.py
rpart-0.1.1.dist-info/WHEEL
rpart-0.1.1.dist-info/METADATA
rpart-0.1.1.dist-info/RECORD
