Metadata-Version: 2.1
Name: rpart
Version: 0.1.1
Summary: 
Author: Qiushi Yan
Author-email: qiushi.yann@gmail.com
Requires-Python: >=3.8,<4.0
Classifier: Programming Language :: Python :: 3
Classifier: Programming Language :: Python :: 3.10
Classifier: Programming Language :: Python :: 3.8
Classifier: Programming Language :: Python :: 3.9
Requires-Dist: pandas (>=1.5.3,<2.0.0)
